capstone_api/__init__.py
capstone_api/canvas_api.py
capstone_api/chrome_api.py
capstone_api/class_api.py
capstone_api/discord_api.py
capstone_api/discord_api_BACKUP_09_21_2022.py
capstone_api/grep_binary.py
capstone_api/yt_dlp_api.py
capstone_api/bin/__init__.py
capstone_api/bin/__main__.py
capstone_api/utils/__init__.py
capstone_api/utils/requests_api.py
capstone_api/utils/tools.py
capstone_api-0.2.145.dist-info/LICENSE
capstone_api-0.2.145.dist-info/METADATA
capstone_api-0.2.145.dist-info/WHEEL
capstone_api-0.2.145.dist-info/entry_points.txt
capstone_api-0.2.145.dist-info/top_level.txt
capstone_api-0.2.145.dist-info/RECORD
